{
  "books": [
    {
      "id": "BK001",
      "name": "The Alchemist",
      "author": "Paulo Coelho",
      "description": "A mystical fable about a young shepherd who embarks on a journey to find a hidden treasure, only to discover it within himself.",
      "genre": ["Fiction", "Philosophical", "Adventure"],
      "language": "English",
      "published_date": "1988-01-01",
      "publisher": "HarperCollins",
      "isbn_13": "978-0062315007",
      "price": {
        "amount": 350.00,
        "currency": "INR",
        "symbol": "₹"
      },
      "stock_quantity": 150,
      "image_url": "https://m.media-amazon.com/images/I/81FPzmB5fgL._SY466_.jpg",
      "rating": 4.5,
      "num_reviews": 1250,
      "bestseller": true,
      "trending": true,
      "categories": ["Fiction", "Bestseller "]
    },
    {
      "id": "BK002",
      "name": "Atomic Habits",
      "author": "James Clear",
      "description": "An easy and proven way to build good habits and break bad ones. Clear distills complex topics into simple behaviors that can be easily applied to daily life and work.",
      "genre": ["Self-Help", "Productivity"],
      "language": "English",
      "published_date": "2018-10-16",
      "publisher": "Avery",
      "isbn_13": "978-0735211292",
      "price": {
        "amount": 499.00,
        "currency": "INR",
        "symbol": "₹"
      },
      "stock_quantity": 200,
      "image_url":"https://m.media-amazon.com/images/I/81F90H7hnML._SY466_.jpg",
     "rating": 4.8,
      "num_reviews": 3500,
      "bestseller": true,
      "trending": true,
      "categories": ["Self-Help", "Bestseller", "Trending"]
    },
    {
      "id": "BK004",
      "name": "The Great Gatsby",
      "author": "F. Scott Fitzgerald",
      "description": "A classic novel exploring themes of decadence, idealism, resistance to change, social upheaval, and excess, creating a portrait of the Jazz Age.",
      "genre": ["Fiction", "Classic"],
      "language": "English",
      "published_date": "1925-04-10",
      "publisher": "Charles Scribner's Sons",
      "isbn_13": "978-0743273565",
      "price": {
        "amount": 250.00,
        "currency": "INR",
        "symbol": "₹"
      },
      "stock_quantity": 100,
      "image_url": "https://m.media-amazon.com/images/I/41zUkv8o1HL._SY445_SX342_.jpg",
      "rating": 4.2,
      "num_reviews": 800,
      "bestseller": false,
      "trending": false,
      "categories": ["Fiction", "Classic Literature"]
    },
    {
      "id": "BK005",
      "name": "मनोविज्ञान की दुनिया (The World of Psychology)",
      "author": "Dr. S. K. Singh",
      "description": "मनोविज्ञान के बुनियादी सिद्धांतों और अवधारणाओं का एक व्यापक परिचय, छात्रों और आम पाठकों के लिए उपयुक्त।",
      "genre": ["Non-Fiction", "Psychology"],
      "language": "Hindi",
      "published_date": "2018-03-15",
      "publisher": "Pearson Education India",
      "isbn_13": "978-9332585210",
      "price": {
        "amount": 420.00,
        "currency": "INR",
        "symbol": "₹"
      },
      "stock_quantity": 60,
      "image_url": "https://m.media-amazon.com/images/I/61xiAvaidNL._AC_UY327_FMwebp_QL65_.jpg",
      "rating": 4.0,
      "num_reviews": 150,
      "bestseller": false,
      "trending": false,
      "categories": ["Non-Fiction", "Hindi Books"]
    },
    {
      "id": "BK007",
      "name": "The Midnight Library",
      "author": "Matt Haig",
      "description": "Between life and death, there is a library. When Nora Seed finds herself faced with the possibility of changing her life for a new one, she must search within herself as she travels through the Midnight Library.",
      "genre": ["Fiction", "Fantasy", "Contemporary"],
      "language": "English",
      "published_date": "2020-08-13",
      "publisher": "Canongate Books",
      "isbn_13": "978-1786892718",
      "price": {
        "amount": 400.00,
        "currency": "INR",
        "symbol": "₹"
      },
      "stock_quantity": 120,
      "image_url": "https://m.media-amazon.com/images/I/51y12FpEPwL._AC_UY327_FMwebp_QL65_.jpg",
      "rating": 4.6,
      "num_reviews": 1800,
      "bestseller": true,
      "trending": true,
      "categories": ["Fiction", "Bestseller", "Trending"]
    },
    {
      "id": "BK009",
      "name": "The Psychology of Money",
      "author": "Morgan Housel",
      "description": "Timeless lessons on wealth, greed, and happiness. Housel shares 19 short stories exploring the strange ways people think about money.",
      "genre": ["Non-Fiction", "Finance", "Self-Help"],
      "language": "English",
      "published_date": "2020-09-08",
      "publisher": "Harriman House",
      "isbn_13": "978-0857197689",
      "price": {
        "amount": 550.00,
        "currency": "INR",
        "symbol": "₹"
      },
      "stock_quantity": 160,
      "image_url": "https://m.media-amazon.com/images/I/71XEsXS5RlL._AC_UY327_FMwebp_QL65_.jpg",
      "rating": 4.7,
      "num_reviews": 2000,
      "bestseller": true,
      "trending": true,
      "categories": ["Non-Fiction", "Self-Help", "Bestseller"]
    },
    {
      "id": "BK010",
      "name": "Rich Dad Poor Dad",
      "author": "Robert T. Kiyosaki",
      "description": "Explodes the myth that you need to earn a high income to become rich and explains the difference between working for money and having your money work for you.",
      "genre": ["Self-Help", "Personal Finance"],
      "language": "English",
      "published_date": "1997-04-01",
      "publisher": "Plata Publishing",
      "isbn_13": "978-1612680194",
      "price": {
        "amount": 399.00,
        "currency": "INR",
        "symbol": "₹"
      },
      "stock_quantity": 250,
      "image_url": "https://m.media-amazon.com/images/I/81BE7eeKzAL._AC_UY327_FMwebp_QL65_.jpg",
      "rating": 4.6,
      "num_reviews": 4000,
      "bestseller": true,
      "trending": true,
      "categories": ["Self-Help", "Bestseller", "Trending"]
    },
    {
      "id": "BK012",
      "name": "The Silent Patient",
      "author": "Alex Michaelides",
      "description": "A shocking psychological thriller about a famous painter who shoots her husband and a psychotherapist determined to unravel what happened.",
      "genre": ["Fiction", "Thriller", "Mystery"],
      "language": "English",
      "published_date": "2019-02-05",
      "publisher": "Celadon Books",
      "isbn_13": "978-1250301697",
      "price": {
        "amount": 450.00,
        "currency": "INR",
        "symbol": "₹"
      },
      "stock_quantity": 110,
      "image_url": "https://m.media-amazon.com/images/I/31POcJ7rE5L._AC_UY218_.jpg",
      "rating": 4.3,
      "num_reviews": 2100,
      "bestseller": true,
      "trending": false,
      "categories": ["Fiction", "Bestseller"]
    },
    {
      "id": "BK013",
      "name": "Your Next Five Moves",
      "author": "Patrick Bet-David",
      "description": "A book for entrepreneurs and aspiring leaders on how to strategize and master their next five moves to achieve success.",
      "genre": ["Business", "Self-Help"],
      "language": "English",
      "published_date": "2020-10-13",
      "publisher": "Gallery Books",
      "isbn_13": "978-1982148118",
      "price": {
        "amount": 600.00,
        "currency": "INR",
        "symbol": "₹"
      },
      "stock_quantity": 130,
      "image_url": "https://m.media-amazon.com/images/I/61k0gRvqFFL._AC_UY327_FMwebp_QL65_.jpg",
      "rating": 4.5,
      "num_reviews": 700,
      "bestseller": true,
      "trending": true,
      "categories": ["Self-Help", "Business", "Trending"]
    },
    {
      "id": "BK014",
      "name": "महाभारत (Mahabharata)",
      "author": "Vyasa (Adapted by C. Rajagopalachari)",
      "description": "भारतीय महाकाव्य महाभारत का संक्षिप्त और सुलभ संस्करण, जिसमें इसके प्रमुख कथानक और दार्शनिक पहलुओं को शामिल किया गया है।",
      "genre": ["Mythology", "Epic", "Hinduism"],
      "language": "Hindi",
      "published_date": "1951-01-01",
      "publisher": "Bharatiya Vidya Bhavan",
      "isbn_13": "978-8172763686",
      "price": {
        "amount": 380.00,
        "currency": "INR",
        "symbol": "₹"
      },
      "stock_quantity": 75,
      "image_url": "https://m.media-amazon.com/images/I/71QLqMw+dwL._AC_UY327_FMwebp_QL65_.jpg",
      "rating": 4.7,
      "num_reviews": 400,
      "bestseller": false,
      "trending": false,
      "categories": ["Hindi Books", "Mythology"]
    },
    {
      "id": "BK015",
      "name": "The 7 Habits of Highly Effective People",
      "author": "Stephen Covey",
      "description": "A classic in personal development, offering a holistic, integrated, principle-centered approach for solving personal and professional problems.",
      "genre": ["Self-Help", "Leadership"],
      "language": "English",
      "published_date": "1989-08-15",
      "publisher": "Simon & Schuster",
      "isbn_13": "978-1982137273",
      "price": {
        "amount": 475.00,
        "currency": "INR",
        "symbol": "₹"
      },
      "stock_quantity": 190,
      "image_url": "https://m.media-amazon.com/images/I/81qgEPE6k1L._SY466_.jpg",
      "rating": 4.6,
      "num_reviews": 3000,
      "bestseller": true,
      "trending": false,
      "categories": ["Self-Help", "Bestseller"]
    },
    {
      "id": "BK016",
      "name": "The Harry Potter and the Philosopher's Stone",
      "author": "J.K. Rowling",
      "description": "The first book in the beloved Harry Potter series, introducing the magical world of Hogwarts and the boy who lived.",
      "genre": ["Fantasy", "Young Adult"],
      "language": "English",
      "published_date": "1997-06-26",
      "publisher": "Bloomsbury Publishing",
      "isbn_13": "978-0747532743",
      "price": {
        "amount": 600.00,
        "currency": "INR",
        "symbol": "₹"
      },
      "stock_quantity": 300,
      "image_url": "https://m.media-amazon.com/images/I/81q77Q39nEL._AC_UY327_FMwebp_QL65_.jpg",
      "rating": 4.9,
      "num_reviews": 5000,
      "bestseller": true,
      "trending": true,
      "categories": ["Fiction", "Fantasy", "Bestseller", "Trending"]
    },
    {
      "id": "BK018",
      "name": "The subtle art of not giving a F*ck",
      "author": "Mark Manson",
      "description": "A counterintuitive approach to living a good life, challenging conventional self-help advice.",
      "genre": ["Self-Help", "Philosophy"],
      "language": "English",
      "published_date": "2016-09-13",
      "publisher": "HarperOne",
      "isbn_13": "978-0062457714",
      "price": {
        "amount": 375.00,
        "currency": "INR",
        "symbol": "₹"
      },
      "stock_quantity": 170,
      "image_url": "https://m.media-amazon.com/images/I/71t4GuxLCuL._AC_UY327_FMwebp_QL65_.jpg",
      "rating": 4.4,
      "num_reviews": 2500,
      "bestseller": true,
      "trending": true,
      "categories": ["Self-Help", "Bestseller", "Trending"]
    },
    {
      "id": "BK019",
      "name": "Wings of Fire",
      "author": "A.P.J. Abdul Kalam",
      "description": "The autobiography of former Indian President Dr. A.P.J. Abdul Kalam, chronicling his early life, his work in Indian space and missile programs, and his role as a scientist and president.",
      "genre": ["Autobiography", "Biography", "Inspirational"],
      "language": "English",
      "published_date": "1999-01-01",
      "publisher": "Universities Press",
      "isbn_13": "978-8173711461",
      "price": {
        "amount": 320.00,
        "currency": "INR",
        "symbol": "₹"
      },
      "stock_quantity": 140,
      "image_url": "https://m.media-amazon.com/images/I/71KKZlVjbwL._AC_UY327_FMwebp_QL65_.jpg",
      "rating": 4.7,
      "num_reviews": 1500,
      "bestseller": true,
      "trending": false,
      "categories": ["Non-Fiction", "Bestseller", "Indian Authors"]
    },
    {
      "id": "BK020",
      "name": "The Power of Your Subconscious Mind",
      "author": "Joseph Murphy",
      "description": "A guide to understanding and harnessing the power of the subconscious mind to achieve success and happiness.",
      "genre": ["Self-Help", "Spiritual"],
      "language": "English",
      "published_date": "1963-01-01",
      "publisher": "TarcherPerigee",
      "isbn_13": "978-0425256250",
      "price": {
        "amount": 299.00,
        "currency": "INR",
        "symbol": "₹"
      },
      "stock_quantity": 180,
      "image_url": "https://m.media-amazon.com/images/I/61VAtRuPgYL._SY466_.jpg",
      "rating": 4.5,
      "num_reviews": 1000,
      "bestseller": true,
      "trending": false,
      "categories": ["Self-Help", "Bestseller"]
    },
    {
      "id": "BK021",
      "name": "Dune",
      "author": "Frank Herbert",
      "description": "Set in the distant future amidst a feudal interstellar empire where planetary fiefdoms are controlled by noble houses, this saga tells the story of young Paul Atreides, whose family accepts control of the desert planet Arrakis.",
      "genre": ["Fiction", "Science Fiction", "Adventure"],
      "language": "English",
      "published_date": "1965-08-01",
      "publisher": "Chilton Books",
      "isbn_13": "978-0441172719",
      "price": {
        "amount": 500.00,
        "currency": "INR",
        "symbol": "₹"
      },
      "stock_quantity": 90,
      "image_url": "https://m.media-amazon.com/images/I/91zz3P6dYZL._SY342_.jpg",
      "rating": 4.5,
      "num_reviews": 1900,
      "bestseller": true,
      "trending": true,
      "categories": ["Fiction", "Science Fiction", "Bestseller"]
    },
    {
      "id": "BK022",
      "name": "Project Hail Mary",
      "author": "Andy Weir",
      "description": "An astronaut wakes up on a spaceship with amnesia, tasked with saving humanity from an alien species.",
      "genre": ["Fiction", "Science Fiction", "Adventure"],
      "language": "English",
      "published_date": "2021-05-04",
      "publisher": "Ballantine Books",
      "isbn_13": "978-0593135204",
      "price": {
        "amount": 520.00,
        "currency": "INR",
        "symbol": "₹"
      },
      "stock_quantity": 110,
      "image_url": "https://m.media-amazon.com/images/I/81U0dkXnX4L._SY342_.jpg",
      "rating": 4.7,
      "num_reviews": 2800,
      "bestseller": true,
      "trending": true,
      "categories": ["Fiction", "Science Fiction", "Bestseller"]
    },
    {
      "id": "BK023",
      "name": "The Henna Artist",
      "author": " Alka Joshi",
      "description": "A captivating historical novel set in 1950s India, following the life of a young woman who escapes an arranged marriage to become a renowned henna artist.",
      "genre": ["Fiction", "Historical Fiction"],
      "language": "English",
      "published_date": "2020-03-10",
      "publisher": "Mira",
      "isbn_13": "978-0778309419",
      "price": {
        "amount": 420.00,
        "currency": "INR",
        "symbol": "₹"
      },
      "stock_quantity": 85,
      "image_url": "https://m.media-amazon.com/images/I/814Kbc4QaaS._SY342_.jpg",
      "rating": 4.1,
      "num_reviews": 600,
      "bestseller": false,
      "trending": false,
      "categories": ["Fiction", "Historical Fiction"]
    },
    {
      "id": "BK024",
      "name": "Sapiens: A Brief History of Humankind",
      "author": "Yuval Noah Harari",
      "description": "Explores the entire history of humankind, from the evolution of Homo sapiens to the political and technological revolutions of the 21st century.",
      "genre": ["Non-Fiction", "History", "Science"],
      "language": "English",
      "published_date": "2014-09-04",
      "publisher": "Harper",
      "isbn_13": "978-0062316097",
      "price": {
        "amount": 650.00,
        "currency": "INR",
        "symbol": "₹"
      },
      "stock_quantity": 130,
      "image_url": "https://m.media-amazon.com/images/I/713jIoMO3UL._SY342_.jpg",
      "rating": 4.8,
      "num_reviews": 3200,
      "bestseller": true,
      "trending": true,
      "categories": ["Non-Fiction", "History", "Bestseller"]
    },
    {
      "id": "BK025",
      "name": "Educated",
      "author": "Tara Westover",
      "description": "An unforgettable memoir about a young girl who, kept out of school by her survivalist family, overcomes her challenging upbringing to pursue education and self-reinvention.",
      "genre": ["Non-Fiction", "Biography", "Memoir"],
      "language": "English",
      "published_date": "2018-02-20",
      "publisher": "Random House",
      "isbn_13": "978-0399590504",
      "price": {
        "amount": 480.00,
        "currency": "INR",
        "symbol": "₹"
      },
      "stock_quantity": 100,
      "image_url": "https://m.media-amazon.com/images/I/71N2HZwRo3L._SY342_.jpg",
      "rating": 4.6,
      "num_reviews": 2500,
      "bestseller": true,
      "trending": false,
      "categories": ["Non-Fiction", "Biography", "Bestseller"]
    },
    {
      "id": "BK026",
      "name": "The Diary of a Young Girl",
      "author": "Anne Frank",
      "description": "The poignant and powerful diary of a Jewish girl hiding with her family during the Nazi occupation of the Netherlands.",
      "genre": ["Non-Fiction", "Biography", "History", "Memoir"],
      "language": "English",
      "published_date": "1947-06-25",
      "publisher": "Doubleday",
      "isbn_13": "978-0385474412",
      "price": {
        "amount": 300.00,
        "currency": "INR",
        "symbol": "₹"
      },
      "stock_quantity": 150,
      "image_url": "https://m.media-amazon.com/images/I/61c4oAPwHhL._SY342_.jpg",
      "rating": 4.5,
      "num_reviews": 1800,
      "bestseller": true,
      "trending": false,
      "categories": ["Non-Fiction", "Biography", "History"]
    },
    {
      "id": "BK027",
      "name": "A Short History of Nearly Everything",
      "author": "Bill Bryson",
      "description": "An accessible and humorous journey through the history of science, from the Big Bang to the rise of civilization.",
      "genre": ["Non-Fiction", "History", "Science"],
      "language": "English",
      "published_date": "2003-05-06",
      "publisher": "Broadway Books",
      "isbn_13": "978-0767908184",
      "price": {
        "amount": 580.00,
        "currency": "INR",
        "symbol": "₹"
      },
      "stock_quantity": 95,
      "image_url": "https://m.media-amazon.com/images/I/81IFXnlXNKL._SY342_.jpg",
      "rating": 4.7,
      "num_reviews": 1100,
      "bestseller": false,
      "trending": false,
      "categories": ["Non-Fiction", "History", "Science"]
    },
    {
      "id": "BK028",
      "name": "The Silk Roads: A New History of the World",
      "author": "Peter Frankopan",
      "description": "A revisionist history that re-centers the narrative of world history on the interconnectedness of the Silk Roads.",
      "genre": ["Non-Fiction", "History"],
      "language": "English",
      "published_date": "2015-05-28",
      "publisher": "Bloomsbury Publishing",
      "isbn_13": "978-1408839977",
      "price": {
        "amount": 700.00,
        "currency": "INR",
        "symbol": "₹"
      },
      "stock_quantity": 70,
      "image_url": "https://m.media-amazon.com/images/I/61yJOIZwHWL._SY445_SX342_.jpg",
      "rating": 4.4,
      "num_reviews": 550,
      "bestseller": false,
      "trending": false,
      "categories": ["Non-Fiction", "History"]
    },
 
    {
      "id": "BK030",
      "name": "Steve Jobs",
      "author": "Walter Isaacson",
      "description": "The definitive biography of the co-founder of Apple, based on more than forty interviews with Jobs over two years, as well as interviews with more than one hundred family members, friends, adversaries, competitors, and colleagues.",
      "genre": ["Non-Fiction", "Biography"],
      "language": "English",
      "published_date": "2011-10-24",
      "publisher": "Simon & Schuster",
      "isbn_13": "978-1451648539",
      "price": {
        "amount": 750.00,
        "currency": "INR",
        "symbol": "₹"
      },
      "stock_quantity": 80,
      "image_url": "https://m.media-amazon.com/images/I/4128HeW7RgL._SY445_SX342_.jpg",
      "rating": 4.6,
      "num_reviews": 2200,
      "bestseller": true,
      "trending": false,
      "categories": ["Non-Fiction", "Biography", "Technology"]
    },
    {
      "id": "BK031",
      "name": "Into Thin Air",
      "author": "Jon Krakauer",
      "description": "A gripping firsthand account of the 1996 Everest disaster, where a sudden storm trapped many climbers near the summit.",
      "genre": ["Non-Fiction", "Adventure", "Survival"],
      "language": "English",
      "published_date": "1997-05-15",
      "publisher": "Anchor Books",
      "isbn_13": "978-0385494786",
      "price": {
        "amount": 420.00,
        "currency": "INR",
        "symbol": "₹"
      },
      "stock_quantity": 100,
      "image_url": "https://m.media-amazon.com/images/I/71iQnGnNXSL._SY466_.jpg",
      "rating": 4.5,
      "num_reviews": 900,
      "bestseller": false,
      "trending": false,
      "categories": ["Non-Fiction", "Adventure", "Memoir"]
    },
    {
      "id": "BK032",
      "name": "Wild: From Lost to Found on the Pacific Crest Trail",
      "author": "Cheryl Strayed",
      "description": "A powerful memoir of a woman's solo 1,100-mile hike on the Pacific Crest Trail as she copes with personal tragedy.",
      "genre": ["Non-Fiction", "Adventure", "Memoir"],
      "language": "English",
      "published_date": "2012-03-20",
      "publisher": "Vintage Books",
      "isbn_13": "978-0307476074",
      "price": {
        "amount": 450.00,
        "currency": "INR",
        "symbol": "₹"
      },
      "stock_quantity": 90,
      "image_url": "https://m.media-amazon.com/images/I/71M6e86LzpL._SY466_.jpg",
      "rating": 4.3,
      "num_reviews": 750,
      "bestseller": false,
      "trending": false,
      "categories": ["Non-Fiction", "Adventure", "Memoir"]
    },
    {
      "id": "BK033",
      "name": "The Call of the Wild",
      "author": "Jack London",
      "description": "A classic adventure novel about a domestic dog named Buck who is stolen from his home and sold into the brutal life of an Alaskan sled dog.",
      "genre": ["Fiction", "Adventure", "Classic"],
      "language": "English",
      "published_date": "1903-08-01",
      "publisher": "Macmillan Publishers",
      "isbn_13": "978-0141439241",
      "price": {
        "amount": 200.00,
        "currency": "INR",
        "symbol": "₹"
      },
      "stock_quantity": 120,
      "image_url": "https://m.media-amazon.com/images/I/41JPcn8j93L._SY445_SX342_.jpg",
      "rating": 4.0,
      "num_reviews": 400,
      "bestseller": false,
      "trending": false,
      "categories": ["Fiction", "Adventure", "Classic Literature"]
    },
    {
      "id": "BK034",
      "name": "The Hobbit",
      "author": "J.R.R. Tolkien",
      "description": "A fantasy adventure novel following the quest of hobbit Bilbo Baggins to win a share of the treasure guarded by the dragon Smaug.",
      "genre": ["Fiction", "Adventure", "Fantasy"],
      "language": "English",
      "published_date": "1937-09-21",
      "publisher": "George Allen & Unwin",
      "isbn_13": "978-0345339683",
      "price": {
        "amount": 400.00,
        "currency": "INR",
        "symbol": "₹"
      },
      "stock_quantity": 150,
      "image_url": "https://m.media-amazon.com/images/I/512WlnAvYlL._SY445_SX342_.jpg",
      "rating": 4.6,
      "num_reviews": 1500,
      "bestseller": true,
      "trending": false,
      "categories": ["Fiction", "Adventure", "Fantasy"]
    },
    {
      "id": "BK035",
      "name": "Where the Wild Things Are",
      "author": "Maurice Sendak",
      "description": "A classic children's picture book about a boy named Max who sails to an island inhabited by Wild Things.",
      "genre": ["Children", "Picture Book", "Fantasy"],
      "language": "English",
      "published_date": "1963-01-01",
      "publisher": "Harper & Row",
      "isbn_13": "978-0060254926",
      "price": {
        "amount": 300.00,
        "currency": "INR",
        "symbol": "₹"
      },
      "stock_quantity": 200,
      "image_url": "https://m.media-amazon.com/images/I/611Z5sqkl0L._SX342_SY445_.jpg",
      "rating": 4.8,
      "num_reviews": 1200,
      "bestseller": true,
      "trending": true,
      "categories": ["Children", "Picture Books"]
    },
    {
      "id": "BK036",
      "name": "The Gruffalo",
      "author": "Julia Donaldson",
      "description": "A popular children's story about a mouse who invents a monster, the Gruffalo, to scare away predators, only to discover the Gruffalo is real.",
      "genre": ["Children", "Picture Book"],
      "language": "English",
      "published_date": "1999-03-01",
      "publisher": "Macmillan Children's Books",
      "isbn_13": "978-0333710937",
      "price": {
        "amount": 250.00,
        "currency": "INR",
        "symbol": "₹"
      },
      "stock_quantity": 180,
      "image_url": "https://m.media-amazon.com/images/I/914+Mu5Uy9L._AC_UY327_FMwebp_QL65_.jpg",
      "rating": 4.7,
      "num_reviews": 900,
      "bestseller": true,
      "trending": false,
      "categories": ["Children", "Picture Books"]
    },
    {
      "id": "BK037",
      "name": "Charlotte's Web",
      "author": "E.B. White",
      "description": "A timeless children's novel about a pig named Wilbur and his friendship with a barn spider named Charlotte, who saves him from being slaughtered.",
      "genre": ["Children", "Classic", "Fantasy"],
      "language": "English",
      "published_date": "1952-10-15",
      "publisher": "Harper & Brothers",
      "isbn_13": "978-0064400551",
      "price": {
        "amount": 320.00,
        "currency": "INR",
        "symbol": "₹"
      },
      "stock_quantity": 160,
      "image_url": "https://m.media-amazon.com/images/I/813AS1xuZiL._SY466_.jpg",
      "rating": 4.6,
      "num_reviews": 1100,
      "bestseller": true,
      "trending": false,
      "categories": ["Children", "Classic Literature"]
    }
  ]
}